forgecodecli/__init__.py
forgecodecli/agent.py
forgecodecli/cli.py
forgecodecli/config.py
forgecodecli/secrets.py
forgecodecli/tools.py
forgecodecli-0.1.0.dist-info/METADATA
forgecodecli-0.1.0.dist-info/WHEEL
forgecodecli-0.1.0.dist-info/entry_points.txt
forgecodecli-0.1.0.dist-info/top_level.txt
forgecodecli-0.1.0.dist-info/RECORD
