Metadata-Version: 2.4
Name: forgecodecli
Version: 0.1.0
Summary: A minimal agentic CLI for forging code
Author: Sudhanshu
License: MIT
Requires-Python: >=3.9
Requires-Dist: typer[all]>=0.9.0
Requires-Dist: openai>=1.0.0
Requires-Dist: keyring>=24.0.0
Provides-Extra: dev
Requires-Dist: pytest>=7.0.0; extra == "dev"
Requires-Dist: black>=23.0.0; extra == "dev"
Requires-Dist: ruff>=0.1.0; extra == "dev"
